pyqmt.py
pyqmt-1.0.5.dist-info/METADATA
pyqmt-1.0.5.dist-info/WHEEL
pyqmt-1.0.5.dist-info/top_level.txt
pyqmt-1.0.5.dist-info/RECORD
