Metadata-Version: 2.4
Name: pyqmt
Version: 1.0.5
Summary: 基于miniQMT进行简化的量化交易库
Author: 量化交易汤姆猫
Keywords: qmt,miniqmt,quant
Classifier: Programming Language :: Python :: 3
Classifier: Operating System :: OS Independent
Requires-Python: >=3.8
Requires-Dist: pandas
